bof/__init__.py
bof/base.py
bof/device.py
bof/network.py
bof/packet.py
bof/layers/__init__.py
bof/layers/chicken/__init__.py
bof/layers/chicken/chicken_packet.py
bof/layers/knx/__init__.py
bof/layers/knx/knx_constants.py
bof/layers/knx/knx_functions.py
bof/layers/knx/knx_messages.py
bof/layers/knx/knx_network.py
bof/layers/knx/knx_packet.py
bof/layers/lldp/__init__.py
bof/layers/lldp/lldp_constants.py
bof/layers/lldp/lldp_functions.py
bof/layers/modbus/__init__.py
bof/layers/modbus/modbus_network.py
bof/layers/modbus/modbus_packet.py
bof/layers/profinet/__init__.py
bof/layers/profinet/profinet_constants.py
bof/layers/profinet/profinet_functions.py
bof/layers/raw_scapy/__init__.py
bof/layers/raw_scapy/chicken.py
bof/layers/raw_scapy/knx.py
bof/modules/__init__.py
bof/modules/discovery.py
tests/__init__.py
tests/test_base.py
tests/test_device.py
tests/test_knx.py
tests/test_lldp.py
tests/test_modbus.py
tests/test_network.py
tests/test_packet.py
tests/test_profinet.py
boiboite_opener_framework-1.2.0.dist-info/LICENSE
boiboite_opener_framework-1.2.0.dist-info/METADATA
boiboite_opener_framework-1.2.0.dist-info/WHEEL
boiboite_opener_framework-1.2.0.dist-info/top_level.txt
boiboite_opener_framework-1.2.0.dist-info/RECORD
