Metadata-Version: 2.1
Name: boiboite-opener-framework
Version: 1.2.0
Summary: Industrial network protocols testing framework
Home-page: https://github.com/Orange-Cyberdefense/bof
Author: Claire Vacherot
Author-email: claire.vacherot@orange.com
Classifier: Programming Language :: Python :: 3
Classifier: License :: OSI Approved :: GNU General Public License v3 (GPLv3)
Classifier: Operating System :: OS Independent
Requires-Python: >=3.6
License-File: LICENSE
Requires-Dist: scapy (==2.5.0rc1)
Requires-Dist: packaging
